[
  {
    "name": "Massachusetts Institute of Technology",
    "slug": "mit",
    "posts": [],
    "search_results": []
  },
  {
    "name": "Stanford University",
    "slug": "stanford",
    "posts": [],
    "search_results": []
  },
  {
    "name": "University of Michigan Ann Arbor",
    "slug": "university-of-michigan-ann-arbor",
    "posts": [],
    "search_results": []
  },
  {
    "name": "Georgia Institute of Technology",
    "slug": "georgia-institute-of-technology",
    "posts": [],
    "search_results": []
  },
  {
    "name": "University of Texas Austin",
    "slug": "university-of-texas-austin",
    "posts": [],
    "search_results": []
  }
]